adsmsg/__init__.py
adsmsg/augmentrecord.py
adsmsg/bibrecord.py
adsmsg/boostfactors.py
adsmsg/citation_changes.py
adsmsg/citation_changes_content_type.py
adsmsg/classifyrecord.py
adsmsg/denormalized_record.py
adsmsg/docmatch.py
adsmsg/fulltext_requests.py
adsmsg/fulltext_update.py
adsmsg/master.py
adsmsg/metrics_record.py
adsmsg/msg.py
adsmsg/nonbibrecord.py
adsmsg/orcid_claims.py
adsmsg/status.py
adsmsg/protobuf/__init__.py
adsmsg/protobuf/augmentrecord_pb2.py
adsmsg/protobuf/bibrecord_pb2.py
adsmsg/protobuf/boostfactors_pb2.py
adsmsg/protobuf/citation_changes_content_type_pb2.py
adsmsg/protobuf/citation_changes_pb2.py
adsmsg/protobuf/classifyrecord_pb2.py
adsmsg/protobuf/denormalized_record_pb2.py
adsmsg/protobuf/docmatch_pb2.py
adsmsg/protobuf/fulltext_requests_pb2.py
adsmsg/protobuf/fulltext_update_pb2.py
adsmsg/protobuf/master_pb2.py
adsmsg/protobuf/metrics_pb2.py
adsmsg/protobuf/nonbibrecord_pb2.py
adsmsg/protobuf/orcid_claims_pb2.py
adsmsg/protobuf/status_pb2.py
adsmsg/tests/__init__.py
adsmsg/tests/test_adsmsg.py
adsmsg/tests/test_affiliation_record.py
adsmsg/tests/test_bibrecord.py
adsmsg/tests/test_citation_changes.py
adsmsg/tests/test_denormalized_record.py
adsmsg/tests/test_docmatch.py
adsmsg/tests/test_fulltext_requests.py
adsmsg/tests/test_fulltext_update.py
adsmsg/tests/test_master.py
adsmsg/tests/test_metrics_record.py
adsmsg/tests/test_msg.py
adsmsg/tests/test_nonbibcode_record.py
adsmsg/tests/test_orcid_claims.py
adsmsg-1.3.18.dist-info/LICENSE
adsmsg-1.3.18.dist-info/METADATA
adsmsg-1.3.18.dist-info/WHEEL
adsmsg-1.3.18.dist-info/top_level.txt
adsmsg-1.3.18.dist-info/RECORD
